heatshrink2/__init__.py
heatshrink2/__main__.py
heatshrink2/core.cp312-win_amd64.pyd
heatshrink2/streams.py
heatshrink2/version.py
heatshrink2-0.13.0.dist-info/LICENSE
heatshrink2-0.13.0.dist-info/METADATA
heatshrink2-0.13.0.dist-info/WHEEL
heatshrink2-0.13.0.dist-info/top_level.txt
heatshrink2-0.13.0.dist-info/RECORD
