Metadata-Version: 2.1
Name: heatshrink2
Version: 0.13.0
Summary: Python bindings to the heatshrink library
Home-page: https://github.com/eerimoq/pyheatshrink
Author: Antonis Kalou @ JOHAN Sports, Erik Moqvist
Author-email: antonis@johan-sports.com, erik.moqvist@gmail.com
License: ISC
Keywords: compression binding heatshrink LZSS
Classifier: Programming Language :: Python :: 3
License-File: LICENSE
